README.md
setup.py
LSHkCenters/FuzzyClusteringAlgorithm.py
LSHkCenters/LSHkCenters.py
LSHkCenters/TDef.py
LSHkCenters/TUlti.py
LSHkCenters/__init__.py
LSHkCenters/cvi.py
LSHkCenters/fuzzy_cluster_validity_indices.py
LSHkCenters/LSH/ExammingLSH.py
LSHkCenters/LSH/LSH.py
LSHkCenters/LSH/SimpleHashing.py
LSHkCenters/LSH/__init__.py
LSHkCenters/Measures/DILCA.py
LSHkCenters/Measures/Eskin.py
LSHkCenters/Measures/Goodall1.py
LSHkCenters/Measures/IOF.py
LSHkCenters/Measures/Jia.py
LSHkCenters/Measures/Le_Ho.py
LSHkCenters/Measures/MathUtils.py
LSHkCenters/Measures/Measure.py
LSHkCenters/Measures/MeasureManager.py
LSHkCenters/Measures/New_Lin.py
LSHkCenters/Measures/Nguyen_Huynh.py
LSHkCenters/Measures/OF.py
LSHkCenters/Measures/Overlap.py
LSHkCenters/Measures/__init__.py
lshkcenters.egg-info/PKG-INFO
lshkcenters.egg-info/SOURCES.txt
lshkcenters.egg-info/dependency_links.txt
lshkcenters.egg-info/top_level.txt