Metadata-Version: 2.1
Name: lshkcenters
Version: 1.0.1
Summary: A python package for LSH-k-Centers algorithm
Home-page: https://github.com/
Author: toanstt
Author-email: toan_stt@yahoo.com
License: UNKNOWN
Platform: UNKNOWN
Classifier: Programming Language :: Python :: 3
Classifier: License :: OSI Approved :: MIT License
Classifier: Operating System :: OS Independent
Requires-Python: >=3.6
